metrovlc/__init__.py
metrovlc/buildparser.py
metrovlc/metrovlc.py
metrovlc-0.6.2.dist-info/LICENSE
metrovlc-0.6.2.dist-info/METADATA
metrovlc-0.6.2.dist-info/WHEEL
metrovlc-0.6.2.dist-info/entry_points.txt
metrovlc-0.6.2.dist-info/top_level.txt
metrovlc-0.6.2.dist-info/RECORD
