Metadata-Version: 2.1
Name: metrovlc
Version: 0.6.2
Summary: Command line utility for MetroValencia
Home-page: https://bitbucket.com/penicolas/metrovlc
Author: penicolas
Author-email: png1981@gmail.com
License: UNKNOWN
Platform: UNKNOWN
Classifier: Programming Language :: Python
Classifier: Development Status :: 4 - Beta
Classifier: License :: OSI Approved :: MIT License
Classifier: Operating System :: OS Independent
Classifier: Programming Language :: Python :: 3 :: Only
Classifier: Topic :: Utilities
Classifier: Environment :: Console
Requires-Dist: beautifulsoup4
Requires-Dist: certifi
